SAMUS/__init__.py
SAMUS/modelFile.py
SAMUS/examples/Basic_Usage_Example.ipynb
SAMUS/examples/Modularity_Example.ipynb
SAMUS/examples/__init__.py
SAMUS/examples/basic_usage_example.py
SAMUS/examples/example_traj.csv
SAMUS/examples/example_traj.txt
SAMUS/examples/modularity_example.py
SAMUS/examples/logs/Outputs_basic_example_6.csv
SAMUS/examples/logs/Outputs_modularity_example_6.csv
SAMUS/examples/logs/__init__.py
SAMUS/examples/logs/basic_example_6.txt
SAMUS/examples/logs/modularity_example_6.txt
SAMUS/meshes/3ball.geo
SAMUS/meshes/3ball0.msh
SAMUS/meshes/3ball0.xml
SAMUS/meshes/3ball1.msh
SAMUS/meshes/3ball1.xml
SAMUS/meshes/3ball2.msh
SAMUS/meshes/3ball2.xml
SAMUS/meshes/3ball3.msh
SAMUS/meshes/3ball3.xml
SAMUS/meshes/__init__.py
SAMUS/testing/__init__.py
SAMUS/testing/euler_step_validation.py
SAMUS/testing/example_traj.csv
SAMUS/testing/example_traj.txt
SAMUS/testing/hyperbolic_traj.csv
SAMUS/testing/hyperbolic_traj.txt
SAMUS/testing/mesh_validation.py
SAMUS/testing/trajectory_jump_validation.py
SAMUS/testing/logs/Outputs_coarse_mesh_7.csv
SAMUS/testing/logs/Outputs_doubled_timestep_7.csv
SAMUS/testing/logs/Outputs_finer_mesh_7.csv
SAMUS/testing/logs/Outputs_halved_tolerance_7.csv
SAMUS/testing/logs/Outputs_modularity_test_4.csv
SAMUS/testing/logs/Outputs_standard_timestep_7.csv
SAMUS/testing/logs/Outputs_standard_tolerance_7.csv
SAMUS/testing/logs/__init__.py
SAMUS/testing/logs/coarse_mesh_7.txt
SAMUS/testing/logs/doubled_timestep_7.txt
SAMUS/testing/logs/finer_mesh_7.txt
SAMUS/testing/logs/halved_tolerance_7.txt
SAMUS/testing/logs/modularity_test_4.txt
SAMUS/testing/logs/standard_timestep_7.txt
SAMUS/testing/logs/standard_tolerance_7.txt
SAMUS-1.0.0.dist-info/LICENSE
SAMUS-1.0.0.dist-info/METADATA
SAMUS-1.0.0.dist-info/WHEEL
SAMUS-1.0.0.dist-info/top_level.txt
SAMUS-1.0.0.dist-info/RECORD
