Metadata-Version: 2.1
Name: SAMUS
Version: 1.0.0
Summary: SAMUS package
Home-page: https://github.com/astertaylor/SAMUS
Author: Aster Taylor
Author-email: astertaylor@uchicago.edu
License: LICENSE
Keywords: minor bodies,fluid dynamics,numerics,asteroid,comet,tides,tidal forces,tidal deformation
Classifier: Development Status :: 1 - Planning
Classifier: Intended Audience :: Science/Research
Classifier: License :: OSI Approved :: BSD License
Classifier: Operating System :: POSIX :: Linux
Classifier: Programming Language :: Python :: 3.8
License-File: LICENSE
Requires-Dist: numpy
Requires-Dist: numpy-quaternion
Requires-Dist: pandas
Requires-Dist: scipy
Requires-Dist: mpi4py
